{"summary": [{"config": {"DATASET": "fmnist", "TOTAL_CLIENTS": 100, "CLIENT_FRAC": 0.2, "POISON_FRAC": 0.2, "CREATE_DATASET": false, "RANDOM_DATA": false, "CLASS_RATIO": 10, "MODEL": "basic_cnn0", "LEARNING_RATE": 0.001, "BATCH_SIZE": 32, "LOCAL_EPOCHS": 10, "OPTIMIZER": "adam", "FED_ROUNDS": 60, "TEST_EVERY": 1, "RANDOM_PROCESS": false, "COS_DEFENCE": true, "SEL_METHOD": 1, "REDUCE_LR": 1, "COLLAB_MODE": true, "COLLAB_ALL": true, "CONSIDER_LAYERS": "l1", "GRAD_AGG": true, "FEATURE_FINDING_ALGO": "none", "GRAD_COLLECTION_START": 0, "GRAD_COLLECT_FOR": 40, "CLUSTER_SEP": 0.01, "ALPHA": 0.6, "BETA": 0.8, "GAMMA": 0.1, "TRUST_INC": 2, "TRUST_MODIFY_STRATEGY": 0, "HONEST_PARDON_FACTOR": 1.0, "RESET_AXIS": false, "TRUST_SAMPLING": true, "TRUST_NORMALIZATION": false, "LOG_LEVEL": "ERROR", "JSON_RESULTS": true, "GEN_PLOTS": true, "SAVE_HTML_PLOTS": false}, "mean_mean_poison_class_accs": 84.90299999999999, "std_mean_poison_class_accs": 2.612140118753212, "mean_mean_avg_accs": 89.07289999999999, "std_mean_avg_accs": 0.19061306356070662, "mean_mean_poison_class_f1_scores": 81.88328909274276, "std_mean_poison_class_f1_scores": 0.5345676588727171, "mean_mean_avg_f1_scores": 89.00065596024572, "std_mean_avg_f1_scores": 0.1997138867847783}, {"config": {"DATASET": "fmnist", "TOTAL_CLIENTS": 100, "CLIENT_FRAC": 0.2, "POISON_FRAC": 0.2, "CREATE_DATASET": false, "RANDOM_DATA": false, "CLASS_RATIO": 10, "MODEL": "basic_cnn0", "LEARNING_RATE": 0.001, "BATCH_SIZE": 32, "LOCAL_EPOCHS": 10, "OPTIMIZER": "adam", "FED_ROUNDS": 60, "TEST_EVERY": 1, "RANDOM_PROCESS": false, "COS_DEFENCE": true, "SEL_METHOD": 1, "REDUCE_LR": 1, "COLLAB_MODE": true, "COLLAB_ALL": true, "CONSIDER_LAYERS": "l1", "GRAD_AGG": true, "FEATURE_FINDING_ALGO": "none", "GRAD_COLLECTION_START": 0, "GRAD_COLLECT_FOR": 40, "CLUSTER_SEP": 0.01, "ALPHA": 0.6, "BETA": 0.8, "GAMMA": 0.1, "TRUST_INC": 2, "TRUST_MODIFY_STRATEGY": 1, "HONEST_PARDON_FACTOR": 1.0, "RESET_AXIS": false, "TRUST_SAMPLING": true, "TRUST_NORMALIZATION": false, "LOG_LEVEL": "ERROR", "JSON_RESULTS": true, "GEN_PLOTS": true, "SAVE_HTML_PLOTS": false}, "mean_mean_poison_class_accs": 82.349, "std_mean_poison_class_accs": 1.0647976333557458, "mean_mean_avg_accs": 89.24749999999999, "std_mean_avg_accs": 0.12824741712798501, "mean_mean_poison_class_f1_scores": 82.16972347144932, "std_mean_poison_class_f1_scores": 0.3855179551025513, "mean_mean_avg_f1_scores": 89.1792116785806, "std_mean_avg_f1_scores": 0.1346947580189125}, {"config": {"DATASET": "fmnist", "TOTAL_CLIENTS": 100, "CLIENT_FRAC": 0.2, "POISON_FRAC": 0.2, "CREATE_DATASET": false, "RANDOM_DATA": false, "CLASS_RATIO": 10, "MODEL": "basic_cnn0", "LEARNING_RATE": 0.001, "BATCH_SIZE": 32, "LOCAL_EPOCHS": 10, "OPTIMIZER": "adam", "FED_ROUNDS": 60, "TEST_EVERY": 1, "RANDOM_PROCESS": false, "COS_DEFENCE": true, "SEL_METHOD": 1, "REDUCE_LR": 1, "COLLAB_MODE": true, "COLLAB_ALL": true, "CONSIDER_LAYERS": "l1", "GRAD_AGG": true, "FEATURE_FINDING_ALGO": "none", "GRAD_COLLECTION_START": 0, "GRAD_COLLECT_FOR": 40, "CLUSTER_SEP": 0.01, "ALPHA": 0.6, "BETA": 0.8, "GAMMA": 0.1, "TRUST_INC": 2, "TRUST_MODIFY_STRATEGY": 2, "HONEST_PARDON_FACTOR": 1.0, "RESET_AXIS": false, "TRUST_SAMPLING": true, "TRUST_NORMALIZATION": false, "LOG_LEVEL": "ERROR", "JSON_RESULTS": true, "GEN_PLOTS": true, "SAVE_HTML_PLOTS": false}, "mean_mean_poison_class_accs": 70.85499999999999, "std_mean_poison_class_accs": 3.473580285526729, "mean_mean_avg_accs": 88.54780000000001, "std_mean_avg_accs": 0.32861475925466177, "mean_mean_poison_class_f1_scores": 77.21418005160322, "std_mean_poison_class_f1_scores": 2.7603914508457343, "mean_mean_avg_f1_scores": 88.40574544872841, "std_mean_avg_f1_scores": 0.38271572020360367}, {"config": {"DATASET": "fmnist", "TOTAL_CLIENTS": 100, "CLIENT_FRAC": 0.2, "POISON_FRAC": 0.2, "CREATE_DATASET": false, "RANDOM_DATA": false, "CLASS_RATIO": 10, "MODEL": "basic_cnn0", "LEARNING_RATE": 0.001, "BATCH_SIZE": 32, "LOCAL_EPOCHS": 10, "OPTIMIZER": "adam", "FED_ROUNDS": 60, "TEST_EVERY": 1, "RANDOM_PROCESS": false, "COS_DEFENCE": true, "SEL_METHOD": 1, "REDUCE_LR": 1, "COLLAB_MODE": true, "COLLAB_ALL": true, "CONSIDER_LAYERS": "l1", "GRAD_AGG": true, "FEATURE_FINDING_ALGO": "none", "GRAD_COLLECTION_START": 0, "GRAD_COLLECT_FOR": 40, "CLUSTER_SEP": 0.01, "ALPHA": 0.6, "BETA": 0.8, "GAMMA": 0.1, "TRUST_INC": 2, "TRUST_MODIFY_STRATEGY": 3, "HONEST_PARDON_FACTOR": 1.0, "RESET_AXIS": false, "TRUST_SAMPLING": true, "TRUST_NORMALIZATION": false, "LOG_LEVEL": "ERROR", "JSON_RESULTS": true, "GEN_PLOTS": true, "SAVE_HTML_PLOTS": false}, "mean_mean_poison_class_accs": 80.537, "std_mean_poison_class_accs": 1.265142679700598, "mean_mean_avg_accs": 89.3, "std_mean_avg_accs": 0.18584402061944655, "mean_mean_poison_class_f1_scores": 82.09387869128406, "std_mean_poison_class_f1_scores": 0.46051461221691237, "mean_mean_avg_f1_scores": 89.20473314490138, "std_mean_avg_f1_scores": 0.1862550371838418}]}