{"summary": [{"config": {"DATASET": "cifar10", "TOTAL_CLIENTS": 100, "CLIENT_FRAC": 0.2, "POISON_FRAC": 0.2, "CREATE_DATASET": false, "RANDOM_DATA": false, "CLASS_RATIO": 10, "MODEL": "basic_cnn1", "LEARNING_RATE": 0.001, "BATCH_SIZE": 32, "LOCAL_EPOCHS": 10, "OPTIMIZER": "adam", "FED_ROUNDS": 200, "TEST_EVERY": 1, "RANDOM_PROCESS": false, "COS_DEFENCE": true, "SEL_METHOD": 1, "REDUCE_LR": 1, "COLLAB_MODE": true, "COLLAB_ALL": true, "CONSIDER_LAYERS": "l1", "GRAD_AGG": true, "FEATURE_FINDING_ALGO": "auror", "GRAD_COLLECTION_START": 0, "GRAD_COLLECT_FOR": -1, "CLUSTER_SEP": 0.01, "ALPHA": 0.6, "BETA": 0.8, "GAMMA": 0.1, "TRUST_INC": 2, "TRUST_MODIFY_STRATEGY": 1, "HONEST_PARDON_FACTOR": 1.0, "RESET_AXIS": false, "TRUST_SAMPLING": false, "TRUST_NORMALIZATION": false, "LOG_LEVEL": "ERROR", "JSON_RESULTS": true, "GEN_PLOTS": true, "SAVE_HTML_PLOTS": false}, "mean_mean_poison_class_accs": 33.19136842105263, "std_mean_poison_class_accs": 5.17650344133145, "mean_mean_avg_accs": 53.61590526315789, "std_mean_avg_accs": 1.2718673659486244, "mean_mean_poison_class_f1_scores": 37.65434181868452, "std_mean_poison_class_f1_scores": 2.9274707745971167, "mean_mean_avg_f1_scores": 52.94828241466307, "std_mean_avg_f1_scores": 1.2339410149090604}, {"config": {"DATASET": "cifar10", "TOTAL_CLIENTS": 100, "CLIENT_FRAC": 0.2, "POISON_FRAC": 0.2, "CREATE_DATASET": false, "RANDOM_DATA": false, "CLASS_RATIO": 10, "MODEL": "basic_cnn1", "LEARNING_RATE": 0.001, "BATCH_SIZE": 32, "LOCAL_EPOCHS": 10, "OPTIMIZER": "adam", "FED_ROUNDS": 200, "TEST_EVERY": 1, "RANDOM_PROCESS": false, "COS_DEFENCE": true, "SEL_METHOD": 1, "REDUCE_LR": 1, "COLLAB_MODE": true, "COLLAB_ALL": true, "CONSIDER_LAYERS": "l1", "GRAD_AGG": true, "FEATURE_FINDING_ALGO": "auror", "GRAD_COLLECTION_START": 0, "GRAD_COLLECT_FOR": -1, "CLUSTER_SEP": 0.01, "ALPHA": 0.6, "BETA": 0.8, "GAMMA": 0.1, "TRUST_INC": 2, "TRUST_MODIFY_STRATEGY": 1, "HONEST_PARDON_FACTOR": 1.0, "RESET_AXIS": false, "TRUST_SAMPLING": false, "TRUST_NORMALIZATION": true, "LOG_LEVEL": "ERROR", "JSON_RESULTS": true, "GEN_PLOTS": true, "SAVE_HTML_PLOTS": false}, "mean_mean_poison_class_accs": 35.88884210526315, "std_mean_poison_class_accs": 2.3118655368312, "mean_mean_avg_accs": 59.34599999999999, "std_mean_avg_accs": 1.6238162406440861, "mean_mean_poison_class_f1_scores": 42.70611818957063, "std_mean_poison_class_f1_scores": 2.2666130139282936, "mean_mean_avg_f1_scores": 58.8509472590873, "std_mean_avg_f1_scores": 1.655014741889346}, {"config": {"DATASET": "cifar10", "TOTAL_CLIENTS": 100, "CLIENT_FRAC": 0.2, "POISON_FRAC": 0.2, "CREATE_DATASET": false, "RANDOM_DATA": false, "CLASS_RATIO": 10, "MODEL": "basic_cnn1", "LEARNING_RATE": 0.001, "BATCH_SIZE": 32, "LOCAL_EPOCHS": 10, "OPTIMIZER": "adam", "FED_ROUNDS": 200, "TEST_EVERY": 1, "RANDOM_PROCESS": false, "COS_DEFENCE": true, "SEL_METHOD": 1, "REDUCE_LR": 1, "COLLAB_MODE": true, "COLLAB_ALL": true, "CONSIDER_LAYERS": "l1", "GRAD_AGG": true, "FEATURE_FINDING_ALGO": "auror", "GRAD_COLLECTION_START": 0, "GRAD_COLLECT_FOR": -1, "CLUSTER_SEP": 0.01, "ALPHA": 0.6, "BETA": 0.8, "GAMMA": 0.1, "TRUST_INC": 2, "TRUST_MODIFY_STRATEGY": 1, "HONEST_PARDON_FACTOR": 1.0, "RESET_AXIS": false, "TRUST_SAMPLING": true, "TRUST_NORMALIZATION": false, "LOG_LEVEL": "ERROR", "JSON_RESULTS": true, "GEN_PLOTS": true, "SAVE_HTML_PLOTS": false}, "mean_mean_poison_class_accs": 34.61105263157894, "std_mean_poison_class_accs": 3.2826255790937786, "mean_mean_avg_accs": 53.861599999999996, "std_mean_avg_accs": 1.2964961596848545, "mean_mean_poison_class_f1_scores": 38.86913092049325, "std_mean_poison_class_f1_scores": 1.7101908682701883, "mean_mean_avg_f1_scores": 53.151444619829384, "std_mean_avg_f1_scores": 1.326106436053324}, {"config": {"DATASET": "cifar10", "TOTAL_CLIENTS": 100, "CLIENT_FRAC": 0.2, "POISON_FRAC": 0.2, "CREATE_DATASET": false, "RANDOM_DATA": false, "CLASS_RATIO": 10, "MODEL": "basic_cnn1", "LEARNING_RATE": 0.001, "BATCH_SIZE": 32, "LOCAL_EPOCHS": 10, "OPTIMIZER": "adam", "FED_ROUNDS": 200, "TEST_EVERY": 1, "RANDOM_PROCESS": false, "COS_DEFENCE": true, "SEL_METHOD": 1, "REDUCE_LR": 1, "COLLAB_MODE": true, "COLLAB_ALL": true, "CONSIDER_LAYERS": "l1", "GRAD_AGG": true, "FEATURE_FINDING_ALGO": "auror", "GRAD_COLLECTION_START": 0, "GRAD_COLLECT_FOR": -1, "CLUSTER_SEP": 0.01, "ALPHA": 0.6, "BETA": 0.8, "GAMMA": 0.1, "TRUST_INC": 2, "TRUST_MODIFY_STRATEGY": 1, "HONEST_PARDON_FACTOR": 1.0, "RESET_AXIS": false, "TRUST_SAMPLING": true, "TRUST_NORMALIZATION": true, "LOG_LEVEL": "ERROR", "JSON_RESULTS": true, "GEN_PLOTS": true, "SAVE_HTML_PLOTS": false}, "mean_mean_poison_class_accs": 35.48336842105263, "std_mean_poison_class_accs": 2.2522791067084103, "mean_mean_avg_accs": 59.452189473684214, "std_mean_avg_accs": 0.8603701829063752, "mean_mean_poison_class_f1_scores": 42.46020967493632, "std_mean_poison_class_f1_scores": 1.3599702242344172, "mean_mean_avg_f1_scores": 58.95206677285013, "std_mean_avg_f1_scores": 0.8490264267548691}]}