{"summary": [{"config": {"DATASET": "cifar10", "TOTAL_CLIENTS": 100, "CLIENT_FRAC": 0.2, "POISON_FRAC": 0.0, "CREATE_DATASET": false, "RANDOM_DATA": false, "CLASS_RATIO": 10, "MODEL": "basic_cnn1", "LEARNING_RATE": 0.001, "BATCH_SIZE": 32, "LOCAL_EPOCHS": 10, "OPTIMIZER": "adam", "FED_ROUNDS": 200, "TEST_EVERY": 1, "RANDOM_PROCESS": false, "COS_DEFENCE": false, "SEL_METHOD": 1, "REDUCE_LR": 1, "COLLAB_MODE": true, "COLLAB_ALL": true, "CONSIDER_LAYERS": "l1", "GRAD_AGG": true, "FEATURE_FINDING_ALGO": "auror", "GRAD_COLLECTION_START": 0, "GRAD_COLLECT_FOR": 30, "CLUSTER_SEP": 1.0, "ALPHA": 0.6, "BETA": 0.8, "GAMMA": 0.1, "TRUST_INC": 2, "TRUST_MODIFY_STRATEGY": 1, "HONEST_PARDON_FACTOR": 1.0, "RESET_AXIS": false, "TRUST_SAMPLING": false, "TRUST_NORMALIZATION": true, "LOG_LEVEL": "ERROR", "JSON_RESULTS": true, "GEN_PLOTS": true, "SAVE_HTML_PLOTS": false}, "mean_mean_poison_class_accs": 45.07094117647059, "std_mean_poison_class_accs": 3.527953730208398, "mean_mean_avg_accs": 59.43382352941177, "std_mean_avg_accs": 3.295039714437924, "mean_mean_poison_class_f1_scores": 47.277563639348074, "std_mean_poison_class_f1_scores": 3.9579097527656724, "mean_mean_avg_f1_scores": 59.18137924015919, "std_mean_avg_f1_scores": 3.318799945943013}, {"config": {"DATASET": "cifar10", "TOTAL_CLIENTS": 100, "CLIENT_FRAC": 0.2, "POISON_FRAC": 0.0, "CREATE_DATASET": false, "RANDOM_DATA": false, "CLASS_RATIO": 10, "MODEL": "basic_cnn1", "LEARNING_RATE": 0.001, "BATCH_SIZE": 32, "LOCAL_EPOCHS": 10, "OPTIMIZER": "adam", "FED_ROUNDS": 200, "TEST_EVERY": 1, "RANDOM_PROCESS": false, "COS_DEFENCE": true, "SEL_METHOD": 1, "REDUCE_LR": 1, "COLLAB_MODE": true, "COLLAB_ALL": true, "CONSIDER_LAYERS": "l1", "GRAD_AGG": true, "FEATURE_FINDING_ALGO": "auror", "GRAD_COLLECTION_START": 0, "GRAD_COLLECT_FOR": 30, "CLUSTER_SEP": 1.0, "ALPHA": 0.6, "BETA": 0.8, "GAMMA": 0.1, "TRUST_INC": 2, "TRUST_MODIFY_STRATEGY": 1, "HONEST_PARDON_FACTOR": 1.0, "RESET_AXIS": false, "TRUST_SAMPLING": false, "TRUST_NORMALIZATION": true, "LOG_LEVEL": "ERROR", "JSON_RESULTS": true, "GEN_PLOTS": true, "SAVE_HTML_PLOTS": false}, "mean_mean_poison_class_accs": 45.80729411764706, "std_mean_poison_class_accs": 2.492226158460239, "mean_mean_avg_accs": 60.55830588235294, "std_mean_avg_accs": 2.3957089035871255, "mean_mean_poison_class_f1_scores": 48.45366547092847, "std_mean_poison_class_f1_scores": 2.772760700973351, "mean_mean_avg_f1_scores": 60.320889677667324, "std_mean_avg_f1_scores": 2.3914452808993536}, {"config": {"DATASET": "cifar10", "TOTAL_CLIENTS": 100, "CLIENT_FRAC": 0.2, "POISON_FRAC": 0.2, "CREATE_DATASET": false, "RANDOM_DATA": false, "CLASS_RATIO": 10, "MODEL": "basic_cnn1", "LEARNING_RATE": 0.001, "BATCH_SIZE": 32, "LOCAL_EPOCHS": 10, "OPTIMIZER": "adam", "FED_ROUNDS": 200, "TEST_EVERY": 1, "RANDOM_PROCESS": false, "COS_DEFENCE": false, "SEL_METHOD": 1, "REDUCE_LR": 1, "COLLAB_MODE": true, "COLLAB_ALL": true, "CONSIDER_LAYERS": "l1", "GRAD_AGG": true, "FEATURE_FINDING_ALGO": "auror", "GRAD_COLLECTION_START": 0, "GRAD_COLLECT_FOR": 30, "CLUSTER_SEP": 1.0, "ALPHA": 0.6, "BETA": 0.8, "GAMMA": 0.1, "TRUST_INC": 2, "TRUST_MODIFY_STRATEGY": 1, "HONEST_PARDON_FACTOR": 1.0, "RESET_AXIS": false, "TRUST_SAMPLING": false, "TRUST_NORMALIZATION": true, "LOG_LEVEL": "ERROR", "JSON_RESULTS": true, "GEN_PLOTS": true, "SAVE_HTML_PLOTS": false}, "mean_mean_poison_class_accs": 37.36, "std_mean_poison_class_accs": 2.241415642634134, "mean_mean_avg_accs": 60.12098823529412, "std_mean_avg_accs": 1.8084675924880655, "mean_mean_poison_class_f1_scores": 44.2352783011478, "std_mean_poison_class_f1_scores": 2.18984239969316, "mean_mean_avg_f1_scores": 59.71227832095057, "std_mean_avg_f1_scores": 1.8355061760605802}, {"config": {"DATASET": "cifar10", "TOTAL_CLIENTS": 100, "CLIENT_FRAC": 0.2, "POISON_FRAC": 0.2, "CREATE_DATASET": false, "RANDOM_DATA": false, "CLASS_RATIO": 10, "MODEL": "basic_cnn1", "LEARNING_RATE": 0.001, "BATCH_SIZE": 32, "LOCAL_EPOCHS": 10, "OPTIMIZER": "adam", "FED_ROUNDS": 200, "TEST_EVERY": 1, "RANDOM_PROCESS": false, "COS_DEFENCE": true, "SEL_METHOD": 1, "REDUCE_LR": 1, "COLLAB_MODE": true, "COLLAB_ALL": true, "CONSIDER_LAYERS": "l1", "GRAD_AGG": true, "FEATURE_FINDING_ALGO": "auror", "GRAD_COLLECTION_START": 0, "GRAD_COLLECT_FOR": 30, "CLUSTER_SEP": 1.0, "ALPHA": 0.6, "BETA": 0.8, "GAMMA": 0.1, "TRUST_INC": 2, "TRUST_MODIFY_STRATEGY": 1, "HONEST_PARDON_FACTOR": 1.0, "RESET_AXIS": false, "TRUST_SAMPLING": false, "TRUST_NORMALIZATION": true, "LOG_LEVEL": "ERROR", "JSON_RESULTS": true, "GEN_PLOTS": true, "SAVE_HTML_PLOTS": false}, "mean_mean_poison_class_accs": 38.68788235294117, "std_mean_poison_class_accs": 0.6831416942292883, "mean_mean_avg_accs": 60.6694705882353, "std_mean_avg_accs": 1.2649680204390799, "mean_mean_poison_class_f1_scores": 45.24327788130995, "std_mean_poison_class_f1_scores": 1.1435025345562788, "mean_mean_avg_f1_scores": 60.30207956895865, "std_mean_avg_f1_scores": 1.240225064341984}]}